mymoney/__init__.py
mymoney/meta_data.json
mymoney/core/__init__.py
mymoney/core/data_classes.py
mymoney/core/data_operations.py
mymoney/core/executer.py
mymoney/core/raw_data_reader.py
mymoney/institutions/__init__.py
mymoney/institutions/amex.py
mymoney/institutions/capitalone.py
mymoney/institutions/chase.py
mymoney/institutions/citi.py
mymoney/institutions/discover.py
mymoney/institutions/institution_base.py
mymoney/institutions/paypal.py
mymoney/institutions/venmo.py
money_manager-0.0.2.dist-info/METADATA
money_manager-0.0.2.dist-info/WHEEL
money_manager-0.0.2.dist-info/top_level.txt
money_manager-0.0.2.dist-info/RECORD
