Metadata-Version: 2.1
Name: money-manager
Version: 0.0.2
Summary: A package to manage your money.
Home-page: https://github.com/MRyderOC/money-manager
Author: Milad Tabrizi
Author-email: milad@miladtabrizi.com
License: GPLv3+
Project-URL: Bug Reports, https://github.com/MRyderOC/money-manager/issues
Project-URL: Source, https://github.com/MRyderOC/money-manager
Keywords: finance,expense,money
Requires-Python: >=3.7, <4
